{
    "version": "0.2",
    "ignorePaths": [],
    "dictionaryDefinitions": [],
    "dictionaries": [],
    "words": [
        "algebraicist",
        "Axiomatising",
        "behaviour",
        "Belnap",
        "biproduct",
        "bisimilar",
        "blackbox",
        "blackboxes",
        "blackboxing",
        "Bothe",
        "characterised",
        "CMOS",
        "coalgebra",
        "coalgebraic",
        "coalgebras",
        "coarity",
        "codomain",
        "colour",
        "colours",
        "combinational",
        "comonoid",
        "compositionality",
        "compositionally",
        "coproduct",
        "denotationally",
        "fixpoint",
        "fixpoints",
        "formalise",
        "Frobenius",
        "functorial",
        "functoriality",
        "functors",
        "generalisation",
        "generalisations",
        "generalise",
        "Generalised",
        "generalises",
        "hypergraphs",
        "infimum",
        "initialise",
        "initialised",
        "Kleene",
        "mechanise",
        "mechanising",
        "monoid",
        "monoidal",
        "morphism",
        "morphisms",
        "multicoloured",
        "normalisable",
        "normalisation",
        "normalised",
        "normalising",
        "optimisation",
        "optimisations",
        "optimising",
        "parameterise",
        "parameterised",
        "pointwise",
        "poset",
        "posets",
        "precompose",
        "precomposing",
        "quotienting",
        "realised",
        "redexes",
        "retime",
        "retiming",
        "semilattices",
        "specialised",
        "stabilise",
        "stabilises",
        "STMC",
        "STMCs",
        "subcircuit",
        "subcircuits",
        "supremum",
        "synthesise",
        "systematise",
        "timestep",
        "unidirectionality",
        "utilising"
    ],
    "ignoreWords": [
        "ermutations"
    ],
    "import": []
}